{
  "Posts": [
    {
      "title": "Angular Basics",
      "body": "Learning components, bindings, and directives.",
      "id": "1",
      "userid": 1,
      "date": "2023-10-01",
      "imgurl": "https://picsum.photos/id/10/800/400",
      "like": false,
      "likes": 15,
      "comments": [
        "Great post!",
        "Very helpful."
      ]
    },
    {
      "title": "Routing in Angular",
      "body": "Understanding routerLink, routes, and navigation.",
      "id": "2",
      "userid": 2,
      "date": "2023-10-05",
      "imgurl": "https://picsum.photos/id/11/800/400",
      "like": true,
      "likes": 32,
      "comments": [
        "Clear explanation!"
      ]
    },
    {
      "title": "Dependency Injection",
      "body": "How Angular injects services and manages dependencies.",
      "id": "3",
      "userid": 3,
      "date": "2023-10-10",
      "imgurl": "https://picsum.photos/id/12/800/400",
      "like": false,
      "likes": 8,
      "comments": []
    },
    {
      "title": "Angular Services",
      "body": "Creating and using services to share data.",
      "id": "4",
      "userid": 4,
      "date": "2023-10-15",
      "imgurl": "https://picsum.photos/id/13/800/400",
      "like": true,
      "likes": 21,
      "comments": [
        "Nice example!"
      ]
    },
    {
      "title": "RxJS Observables",
      "body": "Using observables to handle asynchronous data.",
      "id": "5",
      "userid": 5,
      "date": "2023-10-20",
      "imgurl": "https://picsum.photos/id/14/800/400",
      "like": false,
      "likes": 45,
      "comments": [
        "Game-changer!",
        "Thanks for sharing."
      ]
    },
    {
      "title": "Template vs Reactive Forms",
      "body": "Choosing the right form strategy in Angular.",
      "id": "6",
      "userid": 6,
      "date": "2023-10-25",
      "imgurl": "https://picsum.photos/id/15/800/400",
      "like": false,
      "likes": 12,
      "comments": [
        "Which one is better?"
      ]
    },
    {
      "title": "Component Communication",
      "body": "Passing data with @Input and @Output decorators.",
      "id": "7",
      "userid": 7,
      "date": "2023-11-01",
      "imgurl": "https://picsum.photos/id/16/800/400",
      "like": true,
      "likes": 28,
      "comments": [
        "Works like a charm!"
      ]
    },
    {
      "title": "HTTP Client",
      "body": "Fetching data from APIs using HttpClient module.",
      "id": "8",
      "userid": 8,
      "date": "2023-11-05",
      "imgurl": "https://picsum.photos/id/17/800/400",
      "like": false,
      "likes": 36,
      "comments": [
        "How to handle errors?"
      ]
    },
    {
      "title": "Angular Directives",
      "body": "Creating custom directives for DOM manipulation.",
      "id": "9",
      "userid": 9,
      "date": "2023-11-10",
      "imgurl": "https://picsum.photos/id/18/800/400",
      "like": true,
      "likes": 19,
      "comments": [
        "Did not know this!",
        "Very powerful."
      ]
    }
  ],
  "Users": [
    {
      "id": "1",
      "name": "Ali",
      "imgurl": "https://randomuser.me/api/portraits/men/1.jpg",
      "password": "ali123",
      "email": "ali@example.com",
      "username": "ali"
    },
    {
      "id": "2",
      "name": "Mona",
      "imgurl": "https://randomuser.me/api/portraits/women/2.jpg",
      "password": "mona123",
      "email": "mona@example.com",
      "username": "mona"
    },
    {
      "id": "3",
      "name": "Ahmed",
      "imgurl": "https://randomuser.me/api/portraits/men/3.jpg",
      "password": "ahmed123",
      "email": "ahmed@example.com",
      "username": "ahmed"
    },
    {
      "id": "4",
      "name": "Sara",
      "imgurl": "https://randomuser.me/api/portraits/women/4.jpg",
      "password": "sara123",
      "email": "sara@example.com",
      "username": "sara"
    },
    {
      "id": "5",
      "name": "Youssef",
      "imgurl": "https://randomuser.me/api/portraits/men/5.jpg",
      "password": "youssef123",
      "email": "youssef@example.com",
      "username": "youssef"
    },
    {
      "id": "6",
      "name": "Laila",
      "imgurl": "https://randomuser.me/api/portraits/women/6.jpg",
      "password": "laila123",
      "email": "laila@example.com",
      "username": "laila"
    },
    {
      "id": "7",
      "name": "Khaled",
      "imgurl": "https://randomuser.me/api/portraits/men/7.jpg",
      "password": "khaled123",
      "email": "khaled@example.com",
      "username": "khaled"
    },
    {
      "id": "8",
      "name": "Fatma",
      "imgurl": "https://randomuser.me/api/portraits/women/8.jpg",
      "password": "fatma123",
      "email": "fatma@example.com",
      "username": "fatma"
    },
    {
      "id": "9",
      "name": "Hassan",
      "imgurl": "https://randomuser.me/api/portraits/men/9.jpg",
      "password": "hassan123",
      "email": "hassan@example.com",
      "username": "hassan"
    }
  ]
}